blockfacts/__init__.py
blockfacts/rest_client.py
blockfacts/websocket_client.py
blockfacts/api_endpoints/__init__.py
blockfacts/api_endpoints/asset_endpoints.py
blockfacts/api_endpoints/blockfacts_endpoints.py
blockfacts/api_endpoints/exchange_endpoints.py
blockfacts_sdk-1.0.3.dist-info/LICENSE
blockfacts_sdk-1.0.3.dist-info/METADATA
blockfacts_sdk-1.0.3.dist-info/WHEEL
blockfacts_sdk-1.0.3.dist-info/top_level.txt
blockfacts_sdk-1.0.3.dist-info/RECORD
