Metadata-Version: 2.1
Name: blockfacts-sdk
Version: 1.0.3
Summary: Official BlockFacts Python SDK including Rest and WebSocket API support
Home-page: https://github.com/blockfacts-io/blockfacts-python-sdk
Author: BlockFacts Ltd.
Author-email: marko@blockfacts.io
License: MIT
Keywords: BlockFacts,BlockFacts API,Crypto API,Crypto Assets API,Unified Cryptocurrency API,BlockFacts SDK,BlockFacts Python,Blockchain API,Digital Assets API,Digital Asset API
Platform: UNKNOWN
Requires-Python: >=2.7, !=3.0.*, !=3.1.*, !=3.2.*, !=3.3.*, !=3.4.*, <4
Requires-Dist: requests
Requires-Dist: websocket-client
